vcf_contact_generator/__init__.py
vcf_contact_generator/contacts.py
vcf_contact_generator-0.2.0.dist-info/METADATA
vcf_contact_generator-0.2.0.dist-info/WHEEL
vcf_contact_generator-0.2.0.dist-info/license
vcf_contact_generator-0.2.0.dist-info/top_level.txt
vcf_contact_generator-0.2.0.dist-info/RECORD
